setup.py
ndbvalid/__init__.py
ndbvalid/ndbvalid.py
ndbvalid/test_ndbvalid.py
ndbvalid.egg-info/PKG-INFO
ndbvalid.egg-info/SOURCES.txt
ndbvalid.egg-info/dependency_links.txt
ndbvalid.egg-info/top_level.txt