Metadata-Version: 1.1
Name: ndbvalid
Version: 1.3.0
Summary: Validation functions for Google App Enging NDB models.
Home-page: https://github.com/alexyer/ndbvalid
Author: Olexander Yermakov
Author-email: olexander.yermakov@gmail.com
License: MIT
Keywords: validation gae ndb google appengine
Platform: UNKNOWN
Classifier: Development Status :: 5 - Production/Stable
Classifier: Intended Audience :: Developers
Classifier: License :: OSI Approved :: MIT License
